AUTHORS.rst
CONTRIBUTING.rst
HISTORY.rst
LICENSE
MANIFEST.in
Makefile
README.rst
TODO.rst
VERSION
pytest.ini
requirements-dev.txt
requirements-tests.txt
requirements.txt
setup.cfg
setup.py
tox.ini
docs/Makefile
docs/authors.rst
docs/conf.py
docs/contributing.rst
docs/history.rst
docs/index.rst
docs/installation.rst
docs/make.bat
docs/readme.rst
docs/requirements.txt
src/fastavro_codecs/__init__.py
src/fastavro_codecs/__main__.py
src/fastavro_codecs/_base.py
src/fastavro_codecs/_brotli.py
src/fastavro_codecs/_lz4.py
src/fastavro_codecs/_lzma.py
src/fastavro_codecs/_lzo.py
src/fastavro_codecs/_snappy.py
src/fastavro_codecs/_zstd.py
src/fastavro_codecs.egg-info/PKG-INFO
src/fastavro_codecs.egg-info/SOURCES.txt
src/fastavro_codecs.egg-info/dependency_links.txt
src/fastavro_codecs.egg-info/requires.txt
src/fastavro_codecs.egg-info/top_level.txt
tests/test_fastavro_codecs.py
tests/test_main.py
tests/test_package_import.py