Metadata-Version: 1.1
Name: fastavro-codecs
Version: 0.1.0.dev0
Summary: Fastavro codecs.
Home-page: https://github.com/rolando/fastavro-codecs
Author: Rolando Espinoza
Author-email: rolando@rmax.io
License: MIT
Keywords: fastavro-codecs
Platform: UNKNOWN
Classifier: Development Status :: 2 - Pre-Alpha
Classifier: Intended Audience :: Developers
Classifier: License :: OSI Approved :: MIT License
Classifier: Natural Language :: English
Classifier: Programming Language :: Python :: 2
Classifier: Programming Language :: Python :: 2.7
Classifier: Programming Language :: Python :: 3
Classifier: Programming Language :: Python :: 3.4
Classifier: Programming Language :: Python :: 3.5
